jupyterlab_rsw/__init__.py
jupyterlab_rsw/_version.py
jupyterlab_rsw/constants.py
jupyterlab_rsw/handlers.py
jupyterlab_rsw/network.py
jupyterlab_rsw/process.py
jupyterlab_rsw/proxiedServersProvider.py
jupyterlab_rsw/labextension/build_log.json
jupyterlab_rsw/labextension/package.json
jupyterlab_rsw/labextension/schemas/jupyterlab_rsw/package.json.orig
jupyterlab_rsw/labextension/schemas/jupyterlab_rsw/plugin.json
jupyterlab_rsw/labextension/static/lib_index_js.0f9e5472083ed8af3b75.js
jupyterlab_rsw/labextension/static/lib_index_js.0f9e5472083ed8af3b75.js.map
jupyterlab_rsw/labextension/static/remoteEntry.8417ca648fd8dfca170a.js
jupyterlab_rsw/labextension/static/remoteEntry.8417ca648fd8dfca170a.js.map
jupyterlab_rsw/labextension/static/style.js
jupyterlab_rsw/labextension/static/style_index_js.27c4da098d83da7e86d2.js
jupyterlab_rsw/labextension/static/style_index_js.27c4da098d83da7e86d2.js.map
jupyterlab_rsw/labextension/static/vendors-node_modules_css-loader_dist_runtime_api_js-node_modules_css-loader_dist_runtime_cssW-72eba1.1cbc10ae3da61d6c6cdc.js
jupyterlab_rsw/labextension/static/vendors-node_modules_css-loader_dist_runtime_api_js-node_modules_css-loader_dist_runtime_cssW-72eba1.1cbc10ae3da61d6c6cdc.js.map
jupyterlab_rsw-1.0.5.data/data/etc/jupyter/jupyter_server_config.d/jupyterlab_rsw.json
jupyterlab_rsw-1.0.5.data/data/share/jupyter/labextensions/jupyterlab_rsw/build_log.json
jupyterlab_rsw-1.0.5.data/data/share/jupyter/labextensions/jupyterlab_rsw/install.json
jupyterlab_rsw-1.0.5.data/data/share/jupyter/labextensions/jupyterlab_rsw/package.json
jupyterlab_rsw-1.0.5.data/data/share/jupyter/labextensions/jupyterlab_rsw/schemas/jupyterlab_rsw/package.json.orig
jupyterlab_rsw-1.0.5.data/data/share/jupyter/labextensions/jupyterlab_rsw/schemas/jupyterlab_rsw/plugin.json
jupyterlab_rsw-1.0.5.data/data/share/jupyter/labextensions/jupyterlab_rsw/static/lib_index_js.0f9e5472083ed8af3b75.js
jupyterlab_rsw-1.0.5.dist-info/METADATA
jupyterlab_rsw-1.0.5.dist-info/WHEEL
jupyterlab_rsw-1.0.5.dist-info/top_level.txt
jupyterlab_rsw-1.0.5.dist-info/RECORD
