Metadata-Version: 2.1
Name: jupyterlab-rsw
Version: 1.0.5
Summary: Enhance experience of running JupyterLab in RStudio Workbench.
Home-page: https://github.com/rstudio/rstudio-pro/tree/main/src/cpp/session/workspaces/rsp-jupyter-lab
Author: RStudio, PBC
Author-email: 
Keywords: Jupyter,JupyterLab,JupyterLab3
Platform: Linux
Platform: Mac OS X
Platform: Windows
Classifier: License :: OSI Approved :: BSD License
Classifier: Programming Language :: Python
Classifier: Programming Language :: Python :: 3
Classifier: Programming Language :: Python :: 3.7
Classifier: Programming Language :: Python :: 3.8
Classifier: Programming Language :: Python :: 3.9
Classifier: Programming Language :: Python :: 3.10
Classifier: Framework :: Jupyter
Requires-Python: >=3.7
Requires-Dist: jupyter-server (<2,>=1.6)
Requires-Dist: jupyter-server-proxy
